ai2_olmo_eval-0.8.6.dist-info/licenses/LICENSE
olmo_eval/__init__.py
olmo_eval/metrics.py
olmo_eval/tasks.py
olmo_eval/tokenizer.py
olmo_eval/util.py
olmo_eval/version.py
olmo_eval/hf_datasets/ai2_arc/ARC-Challenge/validation/data-00000-of-00001.arrow
olmo_eval/hf_datasets/ai2_arc/ARC-Challenge/validation/dataset_info.json
olmo_eval/hf_datasets/ai2_arc/ARC-Challenge/validation/state.json
olmo_eval/hf_datasets/ai2_arc/ARC-Easy/validation/data-00000-of-00001.arrow
olmo_eval/hf_datasets/ai2_arc/ARC-Easy/validation/dataset_info.json
olmo_eval/hf_datasets/ai2_arc/ARC-Easy/validation/state.json
olmo_eval/hf_datasets/allenai/basic_arithmetic/none/validation/data-00000-of-00001.arrow
olmo_eval/hf_datasets/allenai/basic_arithmetic/none/validation/dataset_info.json
olmo_eval/hf_datasets/allenai/basic_arithmetic/none/validation/state.json
olmo_eval/hf_datasets/boolq/none/validation/data-00000-of-00001.arrow
olmo_eval/hf_datasets/boolq/none/validation/dataset_info.json
olmo_eval/hf_datasets/boolq/none/validation/state.json
olmo_eval/hf_datasets/glue/mrpc/validation/data-00000-of-00001.arrow
olmo_eval/hf_datasets/glue/mrpc/validation/dataset_info.json
olmo_eval/hf_datasets/glue/mrpc/validation/state.json
olmo_eval/hf_datasets/glue/rte/validation/data-00000-of-00001.arrow
olmo_eval/hf_datasets/glue/rte/validation/dataset_info.json
olmo_eval/hf_datasets/glue/rte/validation/state.json
olmo_eval/hf_datasets/glue/sst2/validation/data-00000-of-00001.arrow
olmo_eval/hf_datasets/glue/sst2/validation/dataset_info.json
olmo_eval/hf_datasets/glue/sst2/validation/state.json
olmo_eval/hf_datasets/hails/mmlu_no_train/abstract_algebra/dev/data-00000-of-00001.arrow
olmo_eval/hf_datasets/hails/mmlu_no_train/abstract_algebra/dev/dataset_info.json
olmo_eval/hf_datasets/hails/mmlu_no_train/abstract_algebra/dev/state.json
olmo_eval/hf_datasets/hails/mmlu_no_train/abstract_algebra/test/data-00000-of-00001.arrow
olmo_eval/hf_datasets/hails/mmlu_no_train/abstract_algebra/test/dataset_info.json
ai2_olmo_eval-0.8.6.dist-info/METADATA
ai2_olmo_eval-0.8.6.dist-info/WHEEL
ai2_olmo_eval-0.8.6.dist-info/top_level.txt
ai2_olmo_eval-0.8.6.dist-info/RECORD
