Metadata-Version: 2.4
Name: ai2-olmo-eval
Version: 0.8.6
Summary: In-loop evaluation tasks for language modeling
Author-email: Allen Institute for Artificial Intelligence <olmo@allenai.org>
License:                                  Apache License
Project-URL: Homepage, https://github.com/allenai/OLMo-in-loop-evals
Project-URL: Changelog, https://github.com/allenai/OLMo-in-loop-evals/blob/main/CHANGELOG.md
Requires-Python: >=3.9
License-File: LICENSE
Requires-Dist: torch
Requires-Dist: torchmetrics
Requires-Dist: datasets<4,>=3.6.0
Requires-Dist: cached-path
Requires-Dist: requests
Requires-Dist: packaging
Requires-Dist: importlib_resources
Requires-Dist: tokenizers<0.20,>=0.19.1
Requires-Dist: pyarrow<20,>=19.0
Provides-Extra: dev
Requires-Dist: ruff; extra == "dev"
Requires-Dist: mypy<1.4,>=1.0; extra == "dev"
Requires-Dist: black<24.0,>=23.1; extra == "dev"
Requires-Dist: isort<5.13,>=5.12; extra == "dev"
Requires-Dist: pytest; extra == "dev"
Requires-Dist: twine>=1.11.0; extra == "dev"
Requires-Dist: setuptools; extra == "dev"
Requires-Dist: wheel; extra == "dev"
Requires-Dist: build; extra == "dev"
Requires-Dist: boto3; extra == "dev"
Requires-Dist: google-cloud-storage; extra == "dev"
Provides-Extra: all
Requires-Dist: ai2-olmo-eval[dev]; extra == "all"
Dynamic: license-file
